hello_textual/__about__.py
hello_textual/__init__.py
hello_textual/entry_points.py
hello_textual/hello_app.py
hello_textual/main.py
hello_textual-0.0.2.dist-info/METADATA
hello_textual-0.0.2.dist-info/WHEEL
hello_textual-0.0.2.dist-info/entry_points.txt
hello_textual-0.0.2.dist-info/licenses/LICENSE.txt
hello_textual-0.0.2.dist-info/RECORD
