Metadata-Version: 2.4
Name: hello-textual
Version: 0.0.2
Project-URL: Documentation, https://github.com/U.N. Owen/hello-textual#readme
Project-URL: Issues, https://github.com/U.N. Owen/hello-textual/issues
Project-URL: Source, https://github.com/U.N. Owen/hello-textual
Author-email: "U.N. Owen" <vbd1988@yandex.ru>
License-Expression: MIT
License-File: LICENSE.txt
Classifier: Development Status :: 4 - Beta
Classifier: Programming Language :: Python
Classifier: Programming Language :: Python :: 3.8
Classifier: Programming Language :: Python :: 3.9
Classifier: Programming Language :: Python :: 3.10
Classifier: Programming Language :: Python :: 3.11
Classifier: Programming Language :: Python :: 3.12
Classifier: Programming Language :: Python :: Implementation :: CPython
Classifier: Programming Language :: Python :: Implementation :: PyPy
Requires-Python: >=3.8
Requires-Dist: textual==3.2.0
